autotech_sdk/__init__.py
autotech_sdk/database/__init__.py
autotech_sdk/database/mongo/__init__.py
autotech_sdk/database/mongo/base_model.py
autotech_sdk/database/mongo/base_model_meta.py
autotech_sdk/database/mongo/index_create.py
autotech_sdk/database/mongo/mongo_client.py
autotech_sdk/database/mongo/mongo_config.py
autotech_sdk/database/mongo/setup_collection.py
autotech_sdk/kafka/__init__.py
autotech_sdk/kafka/common/__init__.py
autotech_sdk/kafka/common/confluent_ccloud_lib.py
autotech_sdk/kafka/common/kafka_config.py
autotech_sdk/kafka/consumer/__init__.py
autotech_sdk/kafka/consumer/confluent_consumer.py
autotech_sdk/kafka/publisher/__init__.py
autotech_sdk/kafka/publisher/confluent_publisher.py
autotech_sdk-1.0.3.dist-info/METADATA
autotech_sdk-1.0.3.dist-info/WHEEL
autotech_sdk-1.0.3.dist-info/top_level.txt
autotech_sdk-1.0.3.dist-info/RECORD
