Metadata-Version: 2.1
Name: autotech-sdk
Version: 1.0.3
Summary: Library for neccessary tools for autotech company
Author-email: Autotech2509 <autotech2509@gmail.com>
Project-URL: Homepage, https://github.com/autotech2509/autotech-sdk
Keywords: sdk,autotech
Classifier: License :: OSI Approved :: MIT License
Classifier: Programming Language :: Python
Classifier: Programming Language :: Python :: 3
Requires-Python: >=3.9
Requires-Dist: pymongo (==4.2.0)
Requires-Dist: requests (==2.28.1)
Requires-Dist: certifi (==2022.9.24)
Requires-Dist: confluent-kafka[avro,json,protobuf] (>=1.4.2)
Requires-Dist: Flask (==2.1.2)
Requires-Dist: dacite (==1.6.0)
Requires-Dist: tomli ; python_version < "3.11"
Provides-Extra: dev
Requires-Dist: black ; extra == 'dev'
Requires-Dist: bumpver ; extra == 'dev'
Requires-Dist: isort ; extra == 'dev'
Requires-Dist: pip-tools ; extra == 'dev'
Requires-Dist: pytest ; extra == 'dev'
